openlego/__init__.py
openlego/api.py
openlego/core/__init__.py
openlego/core/abstract_discipline.py
openlego/core/b2k_solver.py
openlego/core/cmdows.py
openlego/core/discipline_component.py
openlego/core/discipline_resolver.py
openlego/core/exec_comp.py
openlego/core/model.py
openlego/core/problem.py
openlego/core/subdriver_component.py
openlego/core/xml_component.py
openlego/docs/__init__.py
openlego/docs/conf.py
openlego/docs/config_params.py
openlego/docs/_utils/__init__.py
openlego/docs/_utils/docutil.py
openlego/docs/_utils/generate_sourcedocs.py
openlego/docs/_utils/patch.py
openlego/docs/_utils/preprocess_tags.py
openlego/partials/__init__.py
openlego/partials/partials.py
openlego/partials/partials.xsd
openlego/test_suite/__init__.py
openlego/test_suite/test_examples/__init__.py
openlego/test_suite/test_examples/sellar_functions.py
openlego/test_suite/test_examples/sellar_competences/__init__.py
openlego/test_suite/test_examples/sellar_competences/sellar_competences_test.py
openlego/test_suite/test_examples/sellar_competences/kb/D_1.py
openlego/test_suite/test_examples/sellar_competences/kb/D_2.py
openlego/test_suite/test_examples/sellar_competences/kb/F.py
openlego/test_suite/test_examples/sellar_competences/kb/G_1.py
openlego/test_suite/test_examples/sellar_competences/kb/G_2.py
openlego/test_suite/test_examples/sellar_competences/kb/H.py
openlego/test_suite/test_examples/sellar_competences/kb/__init__.py
openlego/test_suite/test_examples/sellar_competences_virtual/__init__.py
openlego/test_suite/test_examples/sellar_competences_virtual/disciplines.py
openlego/test_suite/test_examples/sellar_competences_virtual/test_sellar_virtual.py
openlego/test_suite/test_examples/sellar_competences_virtual/sellar_code/__init__.py
openlego/test_suite/test_examples/sellar_competences_virtual/sellar_code/d1.py
openlego/test_suite/test_examples/sellar_competences_virtual/sellar_code/d12.py
openlego/test_suite/test_examples/sellar_competences_virtual/sellar_code/d2.py
openlego-1.5.0.dist-info/LICENSE
openlego-1.5.0.dist-info/METADATA
openlego-1.5.0.dist-info/WHEEL
openlego-1.5.0.dist-info/top_level.txt
openlego-1.5.0.dist-info/RECORD
