Metadata-Version: 2.1
Name: openlego
Version: 1.5.0
Summary: An Open-source link between the AGILE project and the OpenMDAO framework
Home-page: https://github.com/daniel-de-vries/OpenLEGO
Author: Daniël de Vries
Author-email: danieldevries6@gmail.com
License: Apache Software License
Download-URL: https://github.com/daniel-de-vries/OpenLEGO/tarball/1.5.0
Keywords: optimization agile multidisciplinary kadmos openmdao engineering xml cpacs
Platform: UNKNOWN
Classifier: Development Status :: 3 - Alpha
Classifier: Intended Audience :: Science/Research
Classifier: License :: OSI Approved :: Apache Software License
Classifier: Operating System :: MacOS :: MacOS X
Classifier: Operating System :: POSIX :: Linux
Classifier: Operating System :: Microsoft :: Windows
Classifier: Topic :: Scientific/Engineering
Classifier: Programming Language :: Python
Classifier: Programming Language :: Python :: 2.7
Classifier: Programming Language :: Python :: 3.7
Requires-Dist: openmdao (>=2.6.0)
Requires-Dist: lxml
Requires-Dist: numpy
Requires-Dist: cached-property
Requires-Dist: plotly
Requires-Dist: six
Requires-Dist: typing
Provides-Extra: ssbj
Requires-Dist: ssbjkadmos (>=0.1.9) ; extra == 'ssbj'
